Metadata-Version: 2.1
Name: label-studio-tools
Version: 0.0.3
Summary: Label studio common tools
Home-page: https://github.com/heartexlabs/label-studio-tools
Author: Heartex
Author-email: hello@heartex.ai
License: UNKNOWN
Platform: UNKNOWN
Classifier: Programming Language :: Python :: 3
Classifier: License :: OSI Approved :: MIT License
Classifier: Operating System :: OS Independent
Requires-Python: >=3.6
License-File: LICENSE
